sensate
