Metadata-Version: 1.0
Name: sensate
Version: 0.2.1
Summary: Sensaphone hub and sensor abstraction library
Home-page: https://bitbucket.org/invitae/sensate
Author: Naomi Most
Author-email: naomi.most@invitae.com
License: MIT
Platform: UNKNOWN
